pydarg/__init__.py
pydarg/app.py
pydarg/dctargwrapper.py
pydarg/util.py
pydarg-0.1.dist-info/METADATA
pydarg-0.1.dist-info/RECORD
pydarg-0.1.dist-info/WHEEL
pydarg-0.1.dist-info/top_level.txt
