Metadata-Version: 2.1
Name: pydarg
Version: 0.1
Summary: Pure Python decorator for more complex dictionary handling
Home-page: https://github.com/BigJerBD/pydarg
Author: Jeremie Bigras-Dunberry
Author-email: Bigjerbd@gmail.com
License: MIT License
Keywords: python,dictionary,decorator,configuration,utils
Platform: POSIX
Platform: Windows
Platform: Unix
Platform: MacOS
Classifier: Programming Language :: Python :: 3.6
Classifier: Operating System :: OS Independent
Classifier: Topic :: Utilities
